pyshd/__init__.py
pyshd/pyshd.py
pyshd/version.py
pyshd-0.0.1.dist-info/LICENSE
pyshd-0.0.1.dist-info/METADATA
pyshd-0.0.1.dist-info/WHEEL
pyshd-0.0.1.dist-info/top_level.txt
pyshd-0.0.1.dist-info/RECORD
