Metadata-Version: 2.1
Name: pyshd
Version: 0.0.1
Summary: pyshd: pushd contextmanager for python
Home-page: https://github.com/equinor/pyshd
Author: Equinor
Author-email: jegm@equinor.com
License: GNU Lesser General Public License v3
Project-URL: Documentation, https://pyshd.readthedocs.io/
Project-URL: Issue Tracker, https://github.com/equinor/pyshd/issues
Platform: any
